exclusive_or.v
`timescale 10ns/10ns
module exclusive_or(f,a,b);
input a,b;
output f;
wire t1, t2, t3;
nand #5 g1(t1, a, b);
and #5 g2(t2, a, t1);
and #5 g3(t3, b, t1);
nor #5 g4(f, t2, t3);
endmodule

exclusive_or_tb.v
`include "exclusive_or.v"
module exclusive_or_tb;

reg a,b;
wire f;
exclusive_or uut(f,a,b);
initial begin
    $dumpfile("exclusive_or.vcd");
    $dumpvars(0, exclusive_or_tb);

    a = 0;
    b = 0;
    #10;

    a = 0;
    b = 1;
    #10;

    a = 1;
    b = 0;
    #10;

    a = 1;
    b = 1;
    #10;
    $display("test complete");
end

endmodule

exclusive_or.vcd
$date
	Thu Jun 08 20:49:19 2023
$end
$version
	Icarus Verilog
$end
$timescale
	10ns
$end
$scope module exclusive_or_tb $end
$var wire 1 ! f $end
$var reg 1 " a $end
$var reg 1 # b $end
$scope module uut $end
$var wire 1 " a $end
$var wire 1 # b $end
$var wire 1 ! f $end
$var wire 1 $ t1 $end
$var wire 1 % t2 $end
$var wire 1 & t3 $end
$upscope $end
$upscope $end
$enddefinitions $end
$comment Show the parameter values. $end
$dumpall
$end
#0
$dumpvars
x&
x%
x$
0#
0"
x!
$end
#5
0&
0%
1$
#10
1!
1#
#15
1&
#20
0!
0#
1"
#25
0&
1%
#30
1#
#35
0$
1&
#40
0%
0&
#45
1!
