Question2.v
`timescale 1ns/1ns
 module LogicDesign (y,a,b,c,d );
    input a,b,c,d;
    output y;
    wire w1, w2;

    xor #1 (w1,a,c);
    or #1 (w2,d,w1);
    and #1 (y,b,w2);

 endmodule

Question2_tb.v
`include "Question2.v"
`timescale 1ns/1ns

module LogicDesign_tb;
    reg a,b,c,d;
    wire y;

    LogicDesign uut(.y(y), .a(a), .b(b), .c(c), .d(d));
    initial 
    begin
        $dumpfile("Question2.vcd");
        $dumpvars(0,LogicDesign_tb);
        #8 
        a=0;
        b=0;
        c=0;
        d=1;

        #8 
        a=0;
        b=0;
        c=1;
        d=0; 

        #8 
        a=0;
        b=0;
        c=1;
        d=1; 

        #8 
        a=0;
        b=1;
        c=0;
        d=0; 

        #8 
        a=0;
        b=1;
        c=0;
        d=1;     
    end
    initial 
    begin
        $monitor("t=%2d, a=%b, , b=%b c=%b, d=%b, y=%b", $time,a,b,c,d,y);
        #100
        $display("Testing Finish");
        $finish;
    end
endmodule

Question2.vcd
$date
	Sat Sep 09 19:01:55 2023
$end
$version
	Icarus Verilog
$end
$timescale
	1ns
$end
$scope module LogicDesign_tb $end
$var wire 1 ! y $end
$var reg 1 " a $end
$var reg 1 # b $end
$var reg 1 $ c $end
$var reg 1 % d $end
$scope module uut $end
$var wire 1 " a $end
$var wire 1 # b $end
$var wire 1 $ c $end
$var wire 1 % d $end
$var wire 1 & w1 $end
$var wire 1 ' w2 $end
$var wire 1 ! y $end
$upscope $end
$upscope $end
$enddefinitions $end
$comment Show the parameter values. $end
$dumpall
$end
#0
$dumpvars
x'
x&
x%
x$
x#
x"
x!
$end
#8
1%
0$
0#
0"
#9
1'
0!
0&
#16
0%
1$
#17
0'
1&
#18
1'
#24
1%
#32
0%
0$
1#
#33
0&
1!
#34
0'
#35
0!
#40
1%
#41
1'
#42
1!
