Question4.v
`timescale 1ns/1ns
module BCDtoSevenSeg (A,B,C,D,svnsg);

   input A,B,C,D;
   output reg [6:0]svnsg;
   always @ (A,B,C,D)
    begin
        case ({A,B,C,D})

            4'b0000: svnsg = 7'b1111110;
            4'b0001: svnsg = 7'b0110000; 
            4'b0010: svnsg = 7'b1101101;
            4'b0011: svnsg = 7'b1111001; 
            4'b0100: svnsg = 7'b0110011;
            4'b0101: svnsg = 7'b1011011;
            4'b0110: svnsg = 7'b1011111;
            4'b0111: svnsg = 7'b1110000;
            4'b1000: svnsg = 7'b1111111;
            4'b1001: svnsg = 7'b1110011;
            4'b1010: svnsg = 7'b0000000;
            4'b1011: svnsg = 7'b0000000;
            4'b1100: svnsg = 7'b0000000;
            4'b1101: svnsg = 7'b0000000;
            4'b1110: svnsg = 7'b0000000;
            4'b1111: svnsg = 7'b0000000;
     
        endcase
    end      
endmodule

Question4_tb.v
`include "Question4.v"
`timescale 1ns/1ns

module BCDtoSevenSeg_tb;

    reg [3:0]bcd; wire [6:0]svn;

    BCDtoSevenSeg uut(.A(bcd[3]),.B(bcd[2]),.C(bcd[1]),.D(bcd[0]),.svnsg(svn));

    initial 
    begin
        $dumpfile("Question4.vcd");
        $dumpvars(0, BCDtoSevenSeg_tb);

        #5 bcd = 4'b0000;
        #5 bcd = 4'b0001;
        #5 bcd = 4'b0010;    
        #5 bcd = 4'b0011;
        #5 bcd = 4'b0100;
        #5 bcd = 4'b0101;
        #5 bcd = 4'b0110;
        #5 bcd = 4'b0111;
        #5 bcd = 4'b1000;
        #5 bcd = 4'b1001;
        #5 bcd = 4'b1010;
        #5 bcd = 4'b1011;
    end

    initial 
    begin
        $monitor("t = %2d, decBCD = %2d, segarray = %7b", $time, bcd, svn);
        #100 $finish;    
    end
endmodule

Question4.vcd
$date
	Sun Sep 10 16:32:50 2023
$end
$version
	Icarus Verilog
$end
$timescale
	1ns
$end
$scope module BCDtoSevenSeg_tb $end
$var wire 7 ! svn [6:0] $end
$var reg 4 " bcd [3:0] $end
$scope module uut $end
$var wire 1 # A $end
$var wire 1 $ B $end
$var wire 1 % C $end
$var wire 1 & D $end
$var reg 7 ' svnsg [6:0] $end
$upscope $end
$upscope $end
$enddefinitions $end
$comment Show the parameter values. $end
$dumpall
$end
#0
$dumpvars
bx '
x&
x%
x$
x#
bx "
bx !
$end
#5
b1111110 !
b1111110 '
0#
0$
0%
0&
b0 "
#10
b110000 !
b110000 '
1&
b1 "
#15
b1101101 !
b1101101 '
1%
0&
b10 "
#20
b1111001 !
b1111001 '
1&
b11 "
#25
b110011 !
b110011 '
1$
0%
0&
b100 "
#30
b1011011 !
b1011011 '
1&
b101 "
#35
b1011111 !
b1011111 '
1%
0&
b110 "
#40
b1110000 !
b1110000 '
1&
b111 "
#45
b1111111 !
b1111111 '
1#
0$
0%
0&
b1000 "
#50
b1110011 !
b1110011 '
1&
b1001 "
#55
b0 !
b0 '
1%
0&
b1010 "
#60
1&
b1011 "
