Question18.v
`timescale 1ns/1ns

module OctaltoBin (Oct, Bin, Valid);

    input [7:0] Oct;
    output reg [2:0] Bin;
    output Valid;

    assign Valid = |(Oct);
    
    always @(Oct) 
    if (|(Oct) == 0) Bin = 3'bxxx;
    else if(Oct[7] == 1) Bin = 3'b111;
    else if(Oct[6] == 1) Bin = 3'b110;    
    else if(Oct[5] == 1) Bin = 3'b101;
    else if(Oct[4] == 1) Bin = 3'b100;
    else if(Oct[3] == 1) Bin = 3'b011;
    else if(Oct[2] == 1) Bin = 3'b010;
    else if(Oct[1] == 1) Bin = 3'b001;
    else Bin = 3'b000;
    

endmodule

Question18_tb.v
`include "Question18.v"
`timescale 1ns/1ns

module OctaltoBin_tb;

    reg [7:0] Oct;
    wire Valid;
    wire [2:0] Bin;

    OctaltoBin uut(.Oct(Oct), .Valid(Valid), .Bin(Bin));

    initial 
    begin
        $dumpfile("Question18.vcd");
        $dumpvars(0, OctaltoBin_tb);

        #2 Oct = 8'b00000000;
        #2 Oct = 8'b00000001;    
        #2 Oct = 8'b00000010;
        #2 Oct = 8'b00000011;
        #2 Oct = 8'b00000100;
        #2 Oct = 8'b00000101;
        #2 Oct = 8'b00000110;
        #2 Oct = 8'b00000111;
        #2 Oct = 8'b00001000;
        #2 Oct = 8'b00001001;
        #2 Oct = 8'b00001010;
        #2 Oct = 8'b00001011;
        #2 Oct = 8'b00001100;
        #2 Oct = 8'b00001101;
        #2 Oct = 8'b00001110;
        #2 Oct = 8'b00001111;
        #2 Oct = 8'b00010000;
        #2 Oct = 8'b00010001;
        #2 Oct = 8'b00010010;
        #2 Oct = 8'b00010011;
        #2 Oct = 8'b00010100;
        #2 Oct = 8'b00010101;
        #2 Oct = 8'b00010110;
        #2 Oct = 8'b00010111;
        #2 Oct = 8'b00011000;
        #2 Oct = 8'b00011001;
        #2 Oct = 8'b00011010;
        #2 Oct = 8'b00011011;
        #2 Oct = 8'b00011100;
        #2 Oct = 8'b00011101;
        #2 Oct = 8'b00011110;
        #2 Oct = 8'b00011111;
        #2 Oct = 8'b00100000;
        #2 Oct = 8'b00100001;
        #2 Oct = 8'b00100010;
        #2 Oct = 8'b00100011;
        #2 Oct = 8'b00100100;
    end

    initial
    begin
        $monitor("t=%2d, Oct=%8b, Bin=%3b, Valid=%1b", $time, Oct, Bin, Valid);
        #100 $finish;
    end
endmodule

Question18.vcd
$date
	Mon Sep 25 23:59:56 2023
$end
$version
	Icarus Verilog
$end
$timescale
	1ns
$end
$scope module OctaltoBin_tb $end
$var wire 1 ! Valid $end
$var wire 3 " Bin [2:0] $end
$var reg 8 # Oct [7:0] $end
$scope module uut $end
$var wire 8 $ Oct [7:0] $end
$var wire 1 ! Valid $end
$var reg 3 % Bin [2:0] $end
$upscope $end
$upscope $end
$enddefinitions $end
$comment Show the parameter values. $end
$dumpall
$end
#0
$dumpvars
bx %
bx $
bx #
bx "
x!
$end
#2
0!
b0 #
b0 $
#4
b0 "
b0 %
1!
b1 #
b1 $
#6
b1 "
b1 %
b10 #
b10 $
#8
b11 #
b11 $
#10
b10 "
b10 %
b100 #
b100 $
#12
b101 #
b101 $
#14
b110 #
b110 $
#16
b111 #
b111 $
#18
b11 "
b11 %
b1000 #
b1000 $
#20
b1001 #
b1001 $
#22
b1010 #
b1010 $
#24
b1011 #
b1011 $
#26
b1100 #
b1100 $
#28
b1101 #
b1101 $
#30
b1110 #
b1110 $
#32
b1111 #
b1111 $
#34
b100 "
b100 %
b10000 #
b10000 $
#36
b10001 #
b10001 $
#38
b10010 #
b10010 $
#40
b10011 #
b10011 $
#42
b10100 #
b10100 $
#44
b10101 #
b10101 $
#46
b10110 #
b10110 $
#48
b10111 #
b10111 $
#50
b11000 #
b11000 $
#52
b11001 #
b11001 $
#54
b11010 #
b11010 $
#56
b11011 #
b11011 $
#58
b11100 #
b11100 $
#60
b11101 #
b11101 $
#62
b11110 #
b11110 $
#64
b11111 #
b11111 $
#66
b101 "
b101 %
b100000 #
b100000 $
#68
b100001 #
b100001 $
#70
b100010 #
b100010 $
#72
b100011 #
b100011 $
#74
b100100 #
b100100 $
