Question8.v
`timescale 1ns/1ns
module PriorityEncoder (a,b,c,d,p,q,r);
    input a,b,c,d;
    output p,q,r;
    assign p = a|b;
    assign q = a|(c&(!(b)));
    assign r = a|b|c|d;
endmodule

Question8_tb.v
`include "Question8.v"
`timescale 1ns/1ns

module PriorityEncoder_tb;
    
    reg a,b,c,d;
    wire p,q,r;

    PriorityEncoder uut(.a(a), .b(b), .c(c), .d(d), .p(p), .q(q), .r(r));
    initial
    begin
        $dumpfile("Question8.vcd");
        $dumpvars(0, PriorityEncoder_tb);

        #2 {a,b,c,d} = 4'b0100;
        #2 {a,b,c,d} = 4'b0110;
        #2 {a,b,c,d} = 4'b0101;
        #2 {a,b,c,d} = 4'b0010;
        #2 {a,b,c,d} = 4'b0011;
        #2 {a,b,c,d} = 4'b0000;
        #2 {a,b,c,d} = 4'b1000;
        #2 {a,b,c,d} = 4'b1100;
        #2 {a,b,c,d} = 4'b1110;

    end

    initial
    begin
        $monitor("t=%2d, a=%1b, b=%1b, c=%1b, d=%1b, p=%1b, q=%1b, r=%1b", $time,a,b,c,d,p,q,r);
        #25 $finish;
    end

endmodule

Question8.vcd
$date
	Sun Sep 17 14:27:16 2023
$end
$version
	Icarus Verilog
$end
$timescale
	1ns
$end
$scope module PriorityEncoder_tb $end
$var wire 1 ! r $end
$var wire 1 " q $end
$var wire 1 # p $end
$var reg 1 $ a $end
$var reg 1 % b $end
$var reg 1 & c $end
$var reg 1 ' d $end
$scope module uut $end
$var wire 1 $ a $end
$var wire 1 % b $end
$var wire 1 & c $end
$var wire 1 ' d $end
$var wire 1 # p $end
$var wire 1 " q $end
$var wire 1 ! r $end
$upscope $end
$upscope $end
$enddefinitions $end
$comment Show the parameter values. $end
$dumpall
$end
#0
$dumpvars
x'
x&
x%
x$
x#
x"
x!
$end
#2
1!
0"
1#
0$
1%
0&
0'
#4
1&
#6
0&
1'
#8
1"
0#
0%
1&
0'
#10
1'
#12
0"
0!
0&
0'
#14
1!
1#
1"
1$
#16
1%
#18
1&
