Question14.v
`timescale 1ns/1ns

module DigiLogic (a,b,c,d,out1,out2);

    input a,b,c,d;
    output out1, out2;

    wire w1, w2, w3, w4, w5, w6, w7;

    not
        n0(w1,a),
        n1(w2,b),
        n3(out2,w3);
    and
        a0(w4,c,w2),
        a1(w5,b,w1);
    or
        o0(w6,a,w4),
        o1(w3,d,w5),
        o2(out1,w6,w7);
    xor
        xo0(w7,w5,d);
            
endmodule

Question14_tb.v
`include "Question14.v"
`timescale 1ns/1ns

module DigiLogic_tb;
    
    reg a,b,c,d;
    wire out1,out2;

    DigiLogic uut (.a(a), .b(b), .c(c), .d(d), .out1(out1), .out2(out2));

    initial
    begin
        $dumpfile("Question14.vcd");
        $dumpvars(0, DigiLogic_tb);

        #2 {a,b,c,d} = 4'b0000;
        #2 {a,b,c,d} = 4'b0001;
        #2 {a,b,c,d} = 4'b0010;
        #2 {a,b,c,d} = 4'b0011;
        #2 {a,b,c,d} = 4'b0100;
        #2 {a,b,c,d} = 4'b0101;
        #2 {a,b,c,d} = 4'b0110;
        #2 {a,b,c,d} = 4'b0111;
        #2 {a,b,c,d} = 4'b1000;
        #2 {a,b,c,d} = 4'b1001;       
        #2 {a,b,c,d} = 4'b1010;
        #2 {a,b,c,d} = 4'b1011;
        #2 {a,b,c,d} = 4'b1100;
        #2 {a,b,c,d} = 4'b1101;
        #2 {a,b,c,d} = 4'b1110;
        #2 {a,b,c,d} = 4'b1111;
    end

    initial 
    begin
        $monitor("t=%2d, a=%1b, b=%1b, c=%1b, d=%1b, out1=%1b, out2=%1b", $time,a,b,c,d,out1,out2);
        #35 $finish;    
    end
endmodule

Question14.vcd
$date
	Sun Sep 24 02:58:57 2023
$end
$version
	Icarus Verilog
$end
$timescale
	1ns
$end
$scope module DigiLogic_tb $end
$var wire 1 ! out2 $end
$var wire 1 " out1 $end
$var reg 1 # a $end
$var reg 1 $ b $end
$var reg 1 % c $end
$var reg 1 & d $end
$scope module uut $end
$var wire 1 # a $end
$var wire 1 $ b $end
$var wire 1 % c $end
$var wire 1 & d $end
$var wire 1 " out1 $end
$var wire 1 ! out2 $end
$var wire 1 ' w1 $end
$var wire 1 ( w2 $end
$var wire 1 ) w3 $end
$var wire 1 * w4 $end
$var wire 1 + w5 $end
$var wire 1 , w6 $end
$var wire 1 - w7 $end
$upscope $end
$upscope $end
$enddefinitions $end
$comment Show the parameter values. $end
$dumpall
$end
#0
$dumpvars
x-
x,
x+
x*
x)
x(
x'
x&
x%
x$
x#
x"
x!
$end
#2
1!
0"
0)
0-
1'
0,
1(
0+
0*
0#
0$
0%
0&
#4
0!
1"
1)
1-
1&
#6
1,
1!
1"
1*
0)
0-
1%
0&
#8
0!
1)
1-
1&
#10
0,
0!
0(
1+
0*
1)
1-
1$
0%
0&
#12
0"
0-
1&
#14
1"
1-
1%
0&
#16
0"
0-
1&
#18
1!
0)
1"
0'
1,
1(
0+
0-
1#
0$
0%
0&
#20
0!
1)
1-
1&
#22
1!
1*
0)
0-
1%
0&
#24
0!
1)
1-
1&
#26
1!
0(
0*
0)
0-
1$
0%
0&
#28
0!
1)
1-
1&
#30
1!
0)
0-
1%
0&
#32
0!
1)
1-
1&
