Question5.v
`timescale 1ns/1ns
module FullAdder (a,b,cin,s,cout);
    input a,b,cin;
    output s,cout;
    
    assign s= a^b^cin;
    assign cout = (a & b)|(b & cin)|(cin & a);
endmodule

Question5_tb.v
`include "Question5.v"
`timescale 1ns/1ns

module FullAdder_tb;
    reg a,b,cin;
    wire s,cout;

    FullAdder uut(.a(a), .b(b), .cin(cin), .s(s), .cout(cout));

    initial
    begin
        $dumpfile("Question5.vcd");
        $dumpvars(0, FullAdder_tb);

        #5 {a,b,cin} = 3'b001;
        #5 {a,b,cin} = 3'b010;
        #5 {a,b,cin} = 3'b011;
        #5 {a,b,cin} = 3'b100;
        #5 {a,b,cin} = 3'b101;
        #5 {a,b,cin} = 3'b110;
        #5 {a,b,cin} = 3'b111;
        #5 {a,b,cin} = 3'b000;

    end

    initial
    begin
        $monitor("t= %2d, a= %b, b=%b, cin=%b , s=%b, cout=%b", $time, a,b,cin,s,cout);
        #50 $finish;
    end
endmodule

Question5.vcd
$date
	Wed Sep 13 23:15:59 2023
$end
$version
	Icarus Verilog
$end
$timescale
	1ns
$end
$scope module FullAdder_tb $end
$var wire 1 ! s $end
$var wire 1 " cout $end
$var reg 1 # a $end
$var reg 1 $ b $end
$var reg 1 % cin $end
$scope module uut $end
$var wire 1 # a $end
$var wire 1 $ b $end
$var wire 1 % cin $end
$var wire 1 " cout $end
$var wire 1 ! s $end
$upscope $end
$upscope $end
$enddefinitions $end
$comment Show the parameter values. $end
$dumpall
$end
#0
$dumpvars
x%
x$
x#
x"
x!
$end
#5
0"
1!
0#
0$
1%
#10
1!
1$
0%
#15
1"
0!
1%
#20
0"
1!
1#
0$
0%
#25
1"
0!
1%
#30
1"
0!
1$
0%
#35
1!
1%
#40
0"
0!
0#
0$
0%
