Question10.v
`timescale 1ns/1ns

module miniALU (A,B, sel, y);
    input [7:0] A,B;
    input [2:0] sel;
    output reg [7:0] y;

    always @ (A, B, sel) 
    begin
        case (sel)
            3'b000: y <= 8'h00;
            3'b001: y <= A & B;
            3'b010: y <= A | B;
            3'b011: y <= A + B;
            3'b100: y <= A - B;
            3'b101: y <= A ^ B;
            3'b110: y <= ~ A; 
            3'b111: y <= 8'hff;
            default:y <= 8'h00; 
        endcase

    end
endmodule

Question10_tb.v
`include "Question10.v"
`timescale 1ns/1ns

module minALU_tb;

    reg [7:0] A,B;
    reg [2:0] sel;
    wire [7:0] y;

    miniALU uut(.A(A), .B(B), .sel(sel), .y(y));
    
    initial 
    begin
        $dumpfile("Question10.vcd");
        $dumpvars(0, minALU_tb);

        #0 sel = 3'b000;
        #2 A = 8'hf8; B = 8'ha5;
        #3 sel = 3'b001;
        #3 sel = 3'b010;
        #3 sel = 3'b011;
        #3 sel = 3'b100;
        #3 sel = 3'b101;
        #3 sel = 3'b110;
        #3 sel = 3'b111;
    end

    initial
    begin
        $monitor("t=%2d, A=%8b, B=%8b, sel=%3b, out=%8b", $time, A, B, sel, y);
        #25 $finish;
    end

endmodule

Question10.vcd
$date
	Mon Sep 18 13:48:51 2023
$end
$version
	Icarus Verilog
$end
$timescale
	1ns
$end
$scope module minALU_tb $end
$var wire 8 ! y [7:0] $end
$var reg 8 " A [7:0] $end
$var reg 8 # B [7:0] $end
$var reg 3 $ sel [2:0] $end
$scope module uut $end
$var wire 8 % A [7:0] $end
$var wire 8 & B [7:0] $end
$var wire 3 ' sel [2:0] $end
$var reg 8 ( y [7:0] $end
$upscope $end
$upscope $end
$enddefinitions $end
$comment Show the parameter values. $end
$dumpall
$end
#0
$dumpvars
b0 (
b0 '
bx &
bx %
b0 $
bx #
bx "
b0 !
$end
#2
b10100101 #
b10100101 &
b11111000 "
b11111000 %
#5
b10100000 !
b10100000 (
b1 $
b1 '
#8
b11111101 !
b11111101 (
b10 $
b10 '
#11
b10011101 !
b10011101 (
b11 $
b11 '
#14
b1010011 !
b1010011 (
b100 $
b100 '
#17
b1011101 !
b1011101 (
b101 $
b101 '
#20
b111 !
b111 (
b110 $
b110 '
#23
b11111111 !
b11111111 (
b111 $
b111 '
