Question17.v
`timescale 1ns/1ns

module PriorityEnc_4bit (D,Y);
    
    input [3:0] D;
    output reg [1:0] Y;

    always @ (D)
    if (D[3] == 1) Y <= 2'b11;
    else if (D[3]== 0 && D[2]== 1) Y <= 2'b10;
    else if (D[3]== 0 && D[2]== 0 && D[1]== 1) Y <= 2'b01;
    else Y <= 2'b00;
     
endmodule

Question17_tb.v
`include "Question17.v"
`timescale 1ns/1ns

module PriorityEnc_4bit_tb;
    
    reg [3:0] D;
    wire [1:0] Y;

    PriorityEnc_4bit uut(.D(D), .Y(Y));

    initial 
    begin
        $dumpfile("Question17.vcd");
        $dumpvars(0, PriorityEnc_4bit_tb);

        #2 D = 4'b0001;
        #2 D = 4'b0010;    
        #2 D = 4'b0011;
        #2 D = 4'b0100;
        #2 D = 4'b0101;
        #2 D = 4'b0110;
        #2 D = 4'b0111;
        #2 D = 4'b1000;
        #2 D = 4'b1001;
        #2 D = 4'b1010;
        #2 D = 4'b1011;
        #2 D = 4'b1100;
        #2 D = 4'b1101;
        #2 D = 4'b1110;
        #2 D = 4'b1111;
    end

    initial
    begin
        $monitor("t=%2d, D=%4b, Y=%2b", $time,D,Y);
        #35 $finish;
    end
endmodule

Question17.vcd
$date
	Sun Sep 24 05:50:26 2023
$end
$version
	Icarus Verilog
$end
$timescale
	1ns
$end
$scope module PriorityEnc_4bit_tb $end
$var wire 2 ! Y [1:0] $end
$var reg 4 " D [3:0] $end
$scope module uut $end
$var wire 4 # D [3:0] $end
$var reg 2 $ Y [1:0] $end
$upscope $end
$upscope $end
$enddefinitions $end
$comment Show the parameter values. $end
$dumpall
$end
#0
$dumpvars
bx $
bx #
bx "
bx !
$end
#2
b0 !
b0 $
b1 "
b1 #
#4
b1 !
b1 $
b10 "
b10 #
#6
b11 "
b11 #
#8
b10 !
b10 $
b100 "
b100 #
#10
b101 "
b101 #
#12
b110 "
b110 #
#14
b111 "
b111 #
#16
b11 !
b11 $
b1000 "
b1000 #
#18
b1001 "
b1001 #
#20
b1010 "
b1010 #
#22
b1011 "
b1011 #
#24
b1100 "
b1100 #
#26
b1101 "
b1101 #
#28
b1110 "
b1110 #
#30
b1111 "
b1111 #
