Question6.v
`timescale 1ns/1ns

module Bin2Gray (a,b,c,d,gry);
    
    input a,b,c,d;
    output reg [3:0]gry;

    always @ (a,b,c,d)
    begin
        
        gry[3] = a;
        gry[2] = a^b;
        gry[1] = b^c;
        gry[0] = c^d;

    end

endmodule

Question6_tb.v
`timescale 1ns/1ns
`include "Question6.v"

module Bin2Gray_tb;
    reg a,b,c,d;
    wire [3:0]gry;
    Bin2Gray uut (.a(a), .b(b), .c(c), .d(d), .gry(gry));
    initial
    begin
        $dumpfile("Question6.vcd");
        $dumpvars(0, Bin2Gray_tb);

        #5 {a,b,c,d} = 4'b0000;
        #5 {a,b,c,d} = 4'b0001;
        #5 {a,b,c,d} = 4'b1100;
        #5 {a,b,c,d} = 4'b0101;
        #5 {a,b,c,d} = 4'b1010;
        #5 {a,b,c,d} = 4'b0011;
        #5 {a,b,c,d} = 4'b1111;
    end

    initial 
    begin
        $monitor("t=%2d, a=%b, b=%b, c=%b, d=%b Gry = %4b", $time,a,b,c,d,gry);
        #50 $finish;    
    end
endmodule

Question6.vcd
$date
	Mon Sep 11 16:44:25 2023
$end
$version
	Icarus Verilog
$end
$timescale
	1ns
$end
$scope module Bin2Gray_tb $end
$var wire 4 ! gry [3:0] $end
$var reg 1 " a $end
$var reg 1 # b $end
$var reg 1 $ c $end
$var reg 1 % d $end
$scope module uut $end
$var wire 1 " a $end
$var wire 1 # b $end
$var wire 1 $ c $end
$var wire 1 % d $end
$var reg 4 & gry [3:0] $end
$upscope $end
$upscope $end
$enddefinitions $end
$comment Show the parameter values. $end
$dumpall
$end
#0
$dumpvars
bx &
x%
x$
x#
x"
bx !
$end
#5
b0 !
b0 &
0"
0#
0$
0%
#10
b1 !
b1 &
1%
#15
b1010 !
b1010 &
1"
1#
0%
#20
b111 !
b111 &
0"
1%
#25
b1111 !
b1111 &
1"
0#
1$
0%
#30
b10 !
b10 &
0"
1%
#35
b1000 !
b1000 &
1"
1#
