Question9.v
`timescale 1ns/1ns

module MUX16x1 (data, sel, y);
    input [15:0] data;
    input [3:0] sel;
    output y;
    wire w1, w2;
    
    MUX8x1 m1(data[7:0], sel[2:0], w1);
    MUX8x1 m2(data[15:8], sel[2:0], w2);
    MUX2x1 m3(w2,w1, sel[3], y);
endmodule

module MUX8x1 (dat, sett, out);
    input [7:0] dat;
    input [2:0] sett;
    output out;
    assign out = (dat[7] & sett[2] & sett[1] & sett[0])| 
    (dat[6] & sett[2] & sett[1] & !sett[0])|  
    (dat[5] & sett[2] & !sett[1] & sett[0])|  
    (dat[4] & sett[2] & !sett[1] & !sett[0])| 
    (dat[3] & !sett[2] & sett[1] & sett[0])| 
    (dat[2] & !sett[2] & sett[1] & !sett[0])| 
    (dat[1] & !sett[2] & !sett[1] & sett[0])| 
    (dat[0] & !sett[2] & !sett[1] & !sett[0]); 
endmodule

module MUX2x1 (a,b, selo, res);
    input a,b;
    input selo;
    output res;
    assign res = (a & selo) | (b & (!selo));
endmodule

Question9_tb.v
`include "Question9.v"
`timescale 1ns/1ns

module MUX16x1_tb;

    reg [15:0] data;
    reg [3:0] sel;
    wire y;

    MUX16x1 uut(.data(data), .sel(sel), .y(y));

    initial
    begin
        $dumpfile("Question9.vcd");
        $dumpvars(0, MUX16x1_tb);

        #2 data = 16'h2b8d;
        #2 sel = 4'b0000;
        #2 sel = 4'b0001;
        #2 sel = 4'b0010;
        #2 sel = 4'b0011;
        #2 sel = 4'b0100;
        #2 sel = 4'b0101;
        #2 sel = 4'b0110;
        #2 sel = 4'b0111;
        #2 sel = 4'b1000;
        #2 sel = 4'b1001;
        #2 sel = 4'b1010;
        #2 sel = 4'b1011;
        #2 sel = 4'b1100;
        #2 sel = 4'b1101;
        #2 sel = 4'b1110;
        #2 sel = 4'b1111;

    end

    initial
    begin
        $monitor("t=%2d, data=%16b, sel=%3b, out=%1b", $time, data, sel, y);
        #40 $finish;
    end
endmodule

Question9.vcd
$date
	Mon Sep 18 11:47:20 2023
$end
$version
	Icarus Verilog
$end
$timescale
	1ns
$end
$scope module MUX16x1_tb $end
$var wire 1 ! y $end
$var reg 16 " data [15:0] $end
$var reg 4 # sel [3:0] $end
$scope module uut $end
$var wire 16 $ data [15:0] $end
$var wire 4 % sel [3:0] $end
$var wire 1 ! y $end
$var wire 1 & w2 $end
$var wire 1 ' w1 $end
$scope module m1 $end
$var wire 8 ( dat [7:0] $end
$var wire 1 ' out $end
$var wire 3 ) sett [2:0] $end
$upscope $end
$scope module m2 $end
$var wire 8 * dat [7:0] $end
$var wire 1 & out $end
$var wire 3 + sett [2:0] $end
$upscope $end
$scope module m3 $end
$var wire 1 & a $end
$var wire 1 ' b $end
$var wire 1 ! res $end
$var wire 1 , selo $end
$upscope $end
$upscope $end
$upscope $end
$enddefinitions $end
$comment Show the parameter values. $end
$dumpall
$end
#0
$dumpvars
x,
bx +
bx *
bx )
bx (
x'
x&
bx %
bx $
bx #
bx "
x!
$end
#2
b10001101 (
b101011 *
b10101110001101 "
b10101110001101 $
#4
1!
1'
1&
b0 )
b0 +
0,
b0 #
b0 %
#6
0!
0'
1&
b1 )
b1 +
b1 #
b1 %
#8
1!
0&
1'
b10 )
b10 +
b10 #
b10 %
#10
1!
1&
1'
b11 )
b11 +
b11 #
b11 %
#12
0!
0'
0&
b100 )
b100 +
b100 #
b100 %
#14
1&
b101 )
b101 +
b101 #
b101 %
#16
0&
b110 )
b110 +
b110 #
b110 %
#18
1!
1'
b111 )
b111 +
b111 #
b111 %
#20
1&
1!
b0 )
b0 +
1,
b1000 #
b1000 %
#22
1!
0'
1&
b1 )
b1 +
b1001 #
b1001 %
#24
0!
0&
1'
b10 )
b10 +
b1010 #
b1010 %
#26
1!
1&
1'
b11 )
b11 +
b1011 #
b1011 %
#28
0!
0'
0&
b100 )
b100 +
b1100 #
b1100 %
#30
1!
1&
b101 )
b101 +
b1101 #
b1101 %
#32
0!
0&
b110 )
b110 +
b1110 #
b1110 %
#34
1'
b111 )
b111 +
b1111 #
b1111 %
