Question16.v
`timescale 1ns/1ns

module BitAnd (A,Y);

    input [2:0] A;
    output Y;

    assign Y = (A[2]) & (A[1]) & (A[0]);
    
endmodule

Question16_tb.v
`timescale 1ns/1ns
`include "Question16.v"

module BitAnd_tb;

    reg [2:0] A;
    wire Y;

    BitAnd uut (.A(A), .Y(Y));

    initial 
    begin
        $dumpfile("Question16.vcd");
        $dumpvars(0, BitAnd_tb);

        #2 A = 3'b000;
        #2 A = 3'b001;    
        #2 A = 3'b010;
        #2 A = 3'b011;
        #2 A = 3'b100;
        #2 A = 3'b101;
        #2 A = 3'b110;
        #2 A = 3'b111;

    end

    initial
    begin
        $monitor("t=%2d, A=%3b, Y=%1B", $time, A, Y);
        #20 $finish;
    end
endmodule

Question16.vcd
$date
	Sun Sep 24 05:35:01 2023
$end
$version
	Icarus Verilog
$end
$timescale
	1ns
$end
$scope module BitAnd_tb $end
$var wire 1 ! Y $end
$var reg 3 " A [2:0] $end
$scope module uut $end
$var wire 3 # A [2:0] $end
$var wire 1 ! Y $end
$upscope $end
$upscope $end
$enddefinitions $end
$comment Show the parameter values. $end
$dumpall
$end
#0
$dumpvars
bx #
bx "
x!
$end
#2
0!
b0 "
b0 #
#4
b1 "
b1 #
#6
b10 "
b10 #
#8
b11 "
b11 #
#10
b100 "
b100 #
#12
b101 "
b101 #
#14
b110 "
b110 #
#16
1!
b111 "
b111 #
